{
    "WORD [a16]" : { "OpCode" : "", "AddressingMode": "Absolute" },
    "BYTE [d8]" : { "OpCode" : "", "AddressingMode": "Immediate" },
    "LDA #[d8]" : { "OpCode" : "0xa9", "AddressingMode": "Immediate" },
    "LDA [d8]" : { "OpCode" : "0xa5", "AddressingMode": "ZeroPage" },
    "LDA [d8],X" : { "OpCode" : "0xb5", "AddressingMode": "ZeroPageX" },
    "LDA [a16]" : { "OpCode" : "0xad", "AddressingMode": "Absolute" },
    "LDA [a16],X" : { "OpCode" : "0xbd", "AddressingMode": "AbsoluteX" },
    "LDA [a16],Y" : { "OpCode" : "0xb9", "AddressingMode": "AbsoluteY" },
    "LDA ([d8],X)" : { "OpCode" : "0xa1", "AddressingMode": "IndexedIndirectX" },
    "LDA ([d8]),Y" : { "OpCode" : "0xb1", "AddressingMode": "IndexedIndirectY" },
    "STA [d8]" : { "OpCode" : "0x85", "AddressingMode": "ZeroPage" },
    "STA [d8],X" : { "OpCode" : "0x95", "AddressingMode": "ZeroPageX" },
    "STA [a16]" : { "OpCode" : "0x8d", "AddressingMode": "Absolute" },
    "STA [a16],X" : { "OpCode" : "0x9d", "AddressingMode": "AbsoluteX" },
    "STA [a16],Y" : { "OpCode" : "0x99", "AddressingMode": "AbsoluteY" },
    "STA ([d8],X)" : { "OpCode" : "0x81", "AddressingMode": "IndexedIndirectX" },
    "STA ([d8]),Y" : { "OpCode" : "0x91", "AddressingMode": "IndexedIndirectY" },
    "CMP #[d8]" : { "OpCode" : "0xc9", "AddressingMode": "Immediate" },
    "CMP [d8]" : { "OpCode" : "0xc5", "AddressingMode": "ZeroPage" },
    "CMP [d8],X" : { "OpCode" : "0xd5", "AddressingMode": "ZeroPageX" },
    "CMP [a16]" : { "OpCode" : "0xcd", "AddressingMode": "Absolute" },
    "CMP [a16],X" : { "OpCode" : "0xdd", "AddressingMode": "AbsoluteX" },
    "CMP [a16],Y" : { "OpCode" : "0xd9", "AddressingMode": "AbsoluteY" },
    "CMP ([d8],X)" : { "OpCode" : "0xc1", "AddressingMode": "IndexedIndirectX" },
    "CMP ([d8]),Y" : { "OpCode" : "0xd1", "AddressingMode": "IndexedIndirectY" },
    "TXA" : { "OpCode" : "0x8a", "AddressingMode": "Implied" },
    "TAX" : { "OpCode" : "0xaa", "AddressingMode": "Implied" },
    "TYA" : { "OpCode" : "0x98", "AddressingMode": "Implied" },
    "TAY" : { "OpCode" : "0xa8", "AddressingMode": "Implied" },
    "SEC" : { "OpCode" : "0x38", "AddressingMode": "Implied" },
    "CLC" : { "OpCode" : "0x18", "AddressingMode": "Implied" },
    "SEI" : { "OpCode" : "0x78", "AddressingMode": "Implied" },
    "CLI" : { "OpCode" : "0x58", "AddressingMode": "Implied" },
    "SED" : { "OpCode" : "0xf8", "AddressingMode": "Implied" },
    "CLD" : { "OpCode" : "0xd8", "AddressingMode": "Implied" },
    "CLV" : { "OpCode" : "0xb8", "AddressingMode": "Implied" },
    "JMP [a16]" : { "OpCode" : "0x4c", "AddressingMode": "Absolute" },
    "JMP ([a16])" : { "OpCode" : "0x6c", "AddressingMode": "Indirect" },
    "JSR [a16]" : { "OpCode" : "0x20", "AddressingMode": "Absolute" },
    "BCC [r8]" : { "OpCode" : "0x90", "AddressingMode": "Relative" },
    "BCS [r8]" : { "OpCode" : "0xb0", "AddressingMode": "Relative" },
    "BEQ [r8]" : { "OpCode" : "0xf0", "AddressingMode": "Relative" },
    "BNE [r8]" : { "OpCode" : "0xd0", "AddressingMode": "Relative" },
    "BMI [r8]" : { "OpCode" : "0x30", "AddressingMode": "Relative" },
    "BPL [r8]" : { "OpCode" : "0x10", "AddressingMode": "Relative" },
    "BVC [r8]" : { "OpCode" : "0x50", "AddressingMode": "Relative" },
    "BVS [r8]" : { "OpCode" : "0x70", "AddressingMode": "Relative" },
    "RTS" : { "OpCode" : "0x60", "AddressingMode": "Implied" },
    "RTI" : { "OpCode" : "0x40", "AddressingMode": "Implied" },
    "NOP" : { "OpCode" : "0xea", "AddressingMode": "Implied" },
    "BRK" : { "OpCode" : "0x00", "AddressingMode": "Implied" },
    "AND #[d8]" : { "OpCode" : "0x29", "AddressingMode": "Immediate" },
    "AND [d8]" : { "OpCode" : "0x25", "AddressingMode": "ZeroPage" },
    "AND [d8],X" : { "OpCode" : "0x35", "AddressingMode": "ZeroPageX" },
    "AND [a16]" : { "OpCode" : "0x2d", "AddressingMode": "Absolute" },
    "AND [a16],X" : { "OpCode" : "0x3d", "AddressingMode": "AbsoluteX" },
    "AND [a16],Y" : { "OpCode" : "0x39", "AddressingMode": "AbsoluteY" },
    "AND ([d8],X)" : { "OpCode" : "0x21", "AddressingMode": "IndexedIndirectX" },
    "AND ([d8]),Y" : { "OpCode" : "0x31", "AddressingMode": "IndexedIndirectY" },
    "EOR #[d8]" : { "OpCode" : "0x49", "AddressingMode": "Immediate" },
    "EOR [d8]" : { "OpCode" : "0x45", "AddressingMode": "ZeroPage" },
    "EOR [d8],X" : { "OpCode" : "0x55", "AddressingMode": "ZeroPageX" },
    "EOR [a16]" : { "OpCode" : "0x4d", "AddressingMode": "Absolute" },
    "EOR [a16],X" : { "OpCode" : "0x5d", "AddressingMode": "AbsoluteX" },
    "EOR [a16],Y" : { "OpCode" : "0x59", "AddressingMode": "AbsoluteY" },
    "EOR ([d8],X)" : { "OpCode" : "0x41", "AddressingMode": "IndexedIndirectX" },
    "EOR ([d8]),Y" : { "OpCode" : "0x51", "AddressingMode": "IndexedIndirectY" },
    "ORA #[d8]" : { "OpCode" : "0x09", "AddressingMode": "Immediate" },
    "ORA [d8]" : { "OpCode" : "0x05", "AddressingMode": "ZeroPage" },
    "ORA [d8],X" : { "OpCode" : "0x15", "AddressingMode": "ZeroPageX" },
    "ORA [a16]" : { "OpCode" : "0x0d", "AddressingMode": "Absolute" },
    "ORA [a16],X" : { "OpCode" : "0x1d", "AddressingMode": "AbsoluteX" },
    "ORA [a16],Y" : { "OpCode" : "0x19", "AddressingMode": "AbsoluteY" },
    "ORA ([d8],X)" : { "OpCode" : "0x01", "AddressingMode": "IndexedIndirectX" },
    "ORA ([d8]),Y" : { "OpCode" : "0x11", "AddressingMode": "IndexedIndirectY" },
    "ASL A" : { "OpCode" : "0x0a", "AddressingMode": "Accumulator" },
    "ASL [d8]" : { "OpCode" : "0x06", "AddressingMode": "ZeroPage" },
    "ASL [d8],X" : { "OpCode" : "0x16", "AddressingMode": "ZeroPageX" },
    "ASL [a16]" : { "OpCode" : "0x0e", "AddressingMode": "Absolute" },
    "ASL [a16],X" : { "OpCode" : "0x1e", "AddressingMode": "AbsoluteX" },
    "LSR A" : { "OpCode" : "0x4a", "AddressingMode": "Accumulator" },
    "LSR [d8]" : { "OpCode" : "0x46", "AddressingMode": "ZeroPage" },
    "LSR [d8],X" : { "OpCode" : "0x56", "AddressingMode": "ZeroPageX" },
    "LSR [a16]" : { "OpCode" : "0x4e", "AddressingMode": "Absolute" },
    "LSR [a16],X" : { "OpCode" : "0x5e", "AddressingMode": "AbsoluteX" },
    "ROL A" : { "OpCode" : "0x2a", "AddressingMode": "Accumulator" },
    "ROL [d8]" : { "OpCode" : "0x26", "AddressingMode": "ZeroPage" },
    "ROL [d8],X" : { "OpCode" : "0x36", "AddressingMode": "ZeroPageX" },
    "ROL [a16]" : { "OpCode" : "0x2e", "AddressingMode": "Absolute" },
    "ROL [a16],X" : { "OpCode" : "0x3e", "AddressingMode": "AbsoluteX" },
    "ROR A" : { "OpCode" : "0x6a", "AddressingMode": "Accumulator" },
    "ROR [d8]" : { "OpCode" : "0x66", "AddressingMode": "ZeroPage" },
    "ROR [d8],X" : { "OpCode" : "0x76", "AddressingMode": "ZeroPageX" },
    "ROR [a16]" : { "OpCode" : "0x6e", "AddressingMode": "Absolute" },
    "ROR [a16],X" : { "OpCode" : "0x7e", "AddressingMode": "AbsoluteX" },
    "BIT [d8]" : { "OpCode" : "0x24", "AddressingMode": "ZeroPage" },
    "BIT [a16]" : { "OpCode" : "0x2c", "AddressingMode": "Absolute" },
    "ADC #[d8]" : { "OpCode" : "0x69", "AddressingMode": "Immediate" },
    "ADC [d8]" : { "OpCode" : "0x65", "AddressingMode": "ZeroPage" },
    "ADC [d8],X" : { "OpCode" : "0x75", "AddressingMode": "ZeroPageX" },
    "ADC [a16]" : { "OpCode" : "0x6d", "AddressingMode": "Absolute" },
    "ADC [a16],X" : { "OpCode" : "0x7d", "AddressingMode": "AbsoluteX" },
    "ADC [a16],Y" : { "OpCode" : "0x79", "AddressingMode": "AbsoluteY" },
    "ADC ([d8],X)" : { "OpCode" : "0x61", "AddressingMode": "IndexedIndirectX" },
    "ADC ([d8]),Y" : { "OpCode" : "0x71", "AddressingMode": "IndexedIndirectY" },
    "SBC #[d8]" : { "OpCode" : "0xe9", "AddressingMode": "Immediate" },
    "SBC [d8]" : { "OpCode" : "0xe5", "AddressingMode": "ZeroPage" },
    "SBC [d8],X" : { "OpCode" : "0xf5", "AddressingMode": "ZeroPageX" },
    "SBC [a16]" : { "OpCode" : "0xed", "AddressingMode": "Absolute" },
    "SBC [a16],X" : { "OpCode" : "0xfd", "AddressingMode": "AbsoluteX" },
    "SBC [a16],Y" : { "OpCode" : "0xf9", "AddressingMode": "AbsoluteY" },
    "SBC ([d8],X)" : { "OpCode" : "0xe1", "AddressingMode": "IndexedIndirectX" },
    "SBC ([d8]),Y" : { "OpCode" : "0xf1", "AddressingMode": "IndexedIndirectY" },
    "INC [d8]" : { "OpCode" : "0xe6", "AddressingMode": "ZeroPage" },
    "INC [d8],X" : { "OpCode" : "0xf6", "AddressingMode": "ZeroPageX" },
    "INC [a16]" : { "OpCode" : "0xee", "AddressingMode": "Absolute" },
    "INC [a16],X" : { "OpCode" : "0xfe", "AddressingMode": "AbsoluteX" },
    "DEC [d8]" : { "OpCode" : "0xc6", "AddressingMode": "ZeroPage" },
    "DEC [d8],X" : { "OpCode" : "0xd6", "AddressingMode": "ZeroPageX" },
    "DEC [a16]" : { "OpCode" : "0xce", "AddressingMode": "Absolute" },
    "DEC [a16],X" : { "OpCode" : "0xde", "AddressingMode": "AbsoluteX" },
    "PHA" : { "OpCode" : "0x48", "AddressingMode": "Implied" },
    "PLA" : { "OpCode" : "0x68", "AddressingMode": "Implied" },
    "PHP" : { "OpCode" : "0x08", "AddressingMode": "Implied" },
    "PLP" : { "OpCode" : "0x28", "AddressingMode": "Implied" },
    "TXS" : { "OpCode" : "0x9a", "AddressingMode": "Implied" },
    "TSX" : { "OpCode" : "0xba", "AddressingMode": "Implied" },
    "LDX #[d8]" : { "OpCode" : "0xa2", "AddressingMode": "Immediate" },
    "LDX [d8]" : { "OpCode" : "0xa6", "AddressingMode": "ZeroPage" },
    "LDX [d8],Y" : { "OpCode" : "0xb6", "AddressingMode": "ZeroPageY" },
    "LDX [a16]" : { "OpCode" : "0xae", "AddressingMode": "Absolute" },
    "LDX [a16],Y" : { "OpCode" : "0xbe", "AddressingMode": "AbsoluteY" },
    "STX [d8]" : { "OpCode" : "0x86", "AddressingMode": "ZeroPage" },
    "STX [d8],Y" : { "OpCode" : "0x96", "AddressingMode": "ZeroPageY" },
    "STX [a16]" : { "OpCode" : "0x8e", "AddressingMode": "Absolute" },
    "CPX #[d8]" : { "OpCode" : "0xe0", "AddressingMode": "Immediate" },
    "CPX [d8]" : { "OpCode" : "0xe4", "AddressingMode": "ZeroPage" },
    "CPX [a16]" : { "OpCode" : "0xec", "AddressingMode": "Absolute" },
    "INX" : { "OpCode" : "0xe8", "AddressingMode": "Implied" },
    "DEX" : { "OpCode" : "0xca", "AddressingMode": "Implied" },
    "LDY #[d8]" : { "OpCode" : "0xa0", "AddressingMode": "Immediate" },
    "LDY [d8]" : { "OpCode" : "0xa4", "AddressingMode": "ZeroPage" },
    "LDY [d8],X" : { "OpCode" : "0xb4", "AddressingMode": "ZeroPageX" },
    "LDY [a16]" : { "OpCode" : "0xac", "AddressingMode": "Absolute" },
    "LDY [a16],X" : { "OpCode" : "0xbc", "AddressingMode": "AbsoluteX" },
    "STY [d8]" : { "OpCode" : "0x84", "AddressingMode": "ZeroPage" },
    "STY [d8],X" : { "OpCode" : "0x94", "AddressingMode": "ZeroPageX" },
    "STY [a16]" : { "OpCode" : "0x8c", "AddressingMode": "Absolute" },
    "CPY #[d8]" : { "OpCode" : "0xc0", "AddressingMode": "Immediate" },
    "CPY [d8]" : { "OpCode" : "0xc4", "AddressingMode": "ZeroPage" },
    "CPY [a16]" : { "OpCode" : "0xcc", "AddressingMode": "Absolute" },
    "INY" : { "OpCode" : "0xc8", "AddressingMode": "Implied" },
    "DEY" : { "OpCode" : "0x88", "AddressingMode": "Implied" }    
}
